ApacheLocalDomain/__init__.py
ApacheLocalDomain/app/__init__.py
ApacheLocalDomain/app/cli.py
ApacheLocalDomain/app/configs-bk.py
ApacheLocalDomain/app/configs.py
ApacheLocalDomain/app/helper.py
ApacheLocalDomain/app/lib/__init__.py
ApacheLocalDomain/app/lib/checkers.py
ApacheLocalDomain/app/lib/cli_helpers.py
ApacheLocalDomain/app/lib/file_handlers.py
ApacheLocalDomain/app/lib/log.py
ApacheLocalDomain/app/lib/template_handlers.py
ApacheLocalDomain/app/php/__init__.py
ApacheLocalDomain/app/php/cli.py
ApacheLocalDomain/app/wsgi/__init__.py
ApacheLocalDomain/app/wsgi/cli.py
ApacheLocalDomain/templates/__init__.py
ApacheLocalDomain/templates/configuration.template
ApacheLocalDomain/templates/host.template
ApacheLocalDomain/templates/php.template
ApacheLocalDomain/templates/wsgi.template
Apache_Local_Domain-1.1.2.dist-info/DESCRIPTION.rst
Apache_Local_Domain-1.1.2.dist-info/METADATA
Apache_Local_Domain-1.1.2.dist-info/RECORD
Apache_Local_Domain-1.1.2.dist-info/WHEEL
Apache_Local_Domain-1.1.2.dist-info/entry_points.txt
Apache_Local_Domain-1.1.2.dist-info/metadata.json
Apache_Local_Domain-1.1.2.dist-info/top_level.txt
