Metadata-Version: 2.0
Name: Apache-Local-Domain
Version: 1.1.2
Summary: Create Domain in Localhost on Apache2
Home-page: https://gitlab.com/toys-projects/Apache-Local-Domain
Author: Alireza Km
Author-email: alitm28@gmail.com
License: GPLv3
Platform: UNKNOWN
Classifier: Programming Language :: Python :: 3
Classifier: Operating System :: OS Independent
Requires-Dist: click
Requires-Dist: decorator
Requires-Dist: six
Requires-Dist: validators
